quantml/__init__.py
quantml/backtesting/__init__.py
quantml/cli/__init__.py
quantml/core/__init__.py
quantml/data/__init__.py
quantml/evaluation/__init__.py
quantml/features/__init__.py
quantml/models/__init__.py
quantml/signals/__init__.py
quantml/training/__init__.py
quantml/utils/__init__.py
quantml/visualization/__init__.py
quant_torch-0.0.1.dist-info/METADATA
quant_torch-0.0.1.dist-info/WHEEL
quant_torch-0.0.1.dist-info/entry_points.txt
quant_torch-0.0.1.dist-info/top_level.txt
quant_torch-0.0.1.dist-info/RECORD
