Metadata-Version: 2.4
Name: quant-torch
Version: 0.0.1
Summary: ML Forecasting and Backtesting Framework
Author-email: Sycritz <anis.medjdoul01@gmail.com>
License: MIT
Project-URL: Homepage, https://github.com/Sycritz/quant-torch
Project-URL: Documentation, https://github.com/Sycritz/quant-torch#readme
Project-URL: Repository, https://github.com/Sycritz/quant-torch
Keywords: quantitative-finance,machine-learning,backtesting,pytorch
Classifier: Development Status :: 3 - Alpha
Classifier: Intended Audience :: Science/Research
Classifier: License :: OSI Approved :: MIT License
Classifier: Programming Language :: Python :: 3.10
Classifier: Programming Language :: Python :: 3.11
Classifier: Topic :: Scientific/Engineering :: Artificial Intelligence
Requires-Python: >=3.10
Requires-Dist: torch>=2.0
Requires-Dist: pandas>=2.0
Requires-Dist: numpy>=1.24
Requires-Dist: pyyaml>=6.0
Requires-Dist: typer>=0.9
Provides-Extra: dev
Requires-Dist: pytest>=7.0; extra == "dev"
Requires-Dist: pytest-cov>=4.0; extra == "dev"
Requires-Dist: black>=23.0; extra == "dev"
Requires-Dist: ruff>=0.1; extra == "dev"
Requires-Dist: mypy>=1.0; extra == "dev"
Provides-Extra: viz
Requires-Dist: matplotlib>=3.7; extra == "viz"
Requires-Dist: plotly>=5.0; extra == "viz"
